{"docs_main_20-工程规范_20-文档规范.md":"BtNCdVj2","docs_main_10-编码规范_20-css编码规范.md":"DWyEi51i","docs_main_10-编码规范_40-typescript编码规范.md":"CCyBzSVi","index.md":"C_atYyge","docs_main_10-编码规范_10-html编码规范.md":"DqjuswI3","docs_main_40-脚手架cli_10-ants-lint-cli.md":"DwFWP-9R","docs_main_20-工程规范_10-git规范.md":"YHFMLOLZ","docs_main_30-npm包_20-stylelint-config-ants.md":"C0vViyWd","docs_main_30-npm包_10-eslint-config-ants.md":"DQ3EiU6S","docs_main_30-npm包_40-markdownlint-config-ants.md":"KzVT-OtM","docs_main_20-工程规范_30-changelog规范.md":"D0pGHvvL","docs_main_10-编码规范_50-node编码规范.md":"DdXfUmFr","docs_main_30-npm包_30-commitlint-config-ants.md":"DSSgnURl","docs_main_30-npm包_50-eslint-plugin-ants.md":"BaR93uzc","docs_main_10-编码规范_30-javascript编码规范.md":"CzpF3QIR"}
